last2libre/__init__.py
last2libre/exporter.py
last2libre/importer.py
last2libre/last2libre_cli.py
last2libre/scrobblelib.py
last2libre-1.0.0.dev0.dist-info/METADATA
last2libre-1.0.0.dev0.dist-info/RECORD
last2libre-1.0.0.dev0.dist-info/WHEEL
last2libre-1.0.0.dev0.dist-info/entry_points.txt
last2libre-1.0.0.dev0.dist-info/top_level.txt
