Metadata-Version: 2.1
Name: last2libre
Version: 1.0.0.dev0
Summary: Utility to export Last.fm / Libre.fm history and import history into Libre.fm / Gnu.fm
Home-page: https://github.com/jwflory/last2libre
Author: kabniel, Justin W. Flory
License: GNU General Public License v3 or later (GPLv3+)
Keywords: Last.fm,Libre.fm,music,metadata,scrobble,Lastfm,data,tool
Platform: UNKNOWN
Classifier: Development Status :: 4 - Beta
Classifier: Intended Audience :: Developers
Classifier: Intended Audience :: Information Technology
Classifier: License :: OSI Approved :: GNU General Public License v3 or later (GPLv3+)
Classifier: Operating System :: OS Independent
Classifier: Programming Language :: Python :: 3
Classifier: Programming Language :: Python :: 3.6
Classifier: Programming Language :: Python :: 3.7
Classifier: Topic :: Multimedia :: Sound/Audio
Classifier: Topic :: Multimedia :: Sound/Audio :: Analysis
Classifier: Topic :: Scientific/Engineering :: Information Analysis
Classifier: Topic :: System :: Archiving :: Backup
Classifier: Topic :: Utilities
Requires-Python: >=3
